odoo8_addon_account_journal_period_close-8.0.1.0.0.99.dev6-py2.7-nspkg.pth
odoo8_addon_account_journal_period_close-8.0.1.0.0.99.dev6.dist-info/DESCRIPTION.rst
odoo8_addon_account_journal_period_close-8.0.1.0.0.99.dev6.dist-info/METADATA
odoo8_addon_account_journal_period_close-8.0.1.0.0.99.dev6.dist-info/RECORD
odoo8_addon_account_journal_period_close-8.0.1.0.0.99.dev6.dist-info/WHEEL
odoo8_addon_account_journal_period_close-8.0.1.0.0.99.dev6.dist-info/metadata.json
odoo8_addon_account_journal_period_close-8.0.1.0.0.99.dev6.dist-info/namespace_packages.txt
odoo8_addon_account_journal_period_close-8.0.1.0.0.99.dev6.dist-info/top_level.txt
odoo_addons/account_journal_period_close/__init__.py
odoo_addons/account_journal_period_close/__openerp__.py
odoo_addons/account_journal_period_close/i18n/ab.po
odoo_addons/account_journal_period_close/i18n/account_journal_period_close.pot
odoo_addons/account_journal_period_close/i18n/bg.po
odoo_addons/account_journal_period_close/i18n/ca.po
odoo_addons/account_journal_period_close/i18n/ca_ES.po
odoo_addons/account_journal_period_close/i18n/de.po
odoo_addons/account_journal_period_close/i18n/es.po
odoo_addons/account_journal_period_close/i18n/es_ES.po
odoo_addons/account_journal_period_close/i18n/fr.po
odoo_addons/account_journal_period_close/i18n/gl.po
odoo_addons/account_journal_period_close/i18n/pt.po
odoo_addons/account_journal_period_close/i18n/sl.po
odoo_addons/account_journal_period_close/model/__init__.py
odoo_addons/account_journal_period_close/model/account_journal_period.py
odoo_addons/account_journal_period_close/model/account_period.py
odoo_addons/account_journal_period_close/static/description/icon.png
odoo_addons/account_journal_period_close/tests/__init__.py
odoo_addons/account_journal_period_close/tests/test_account_journal_period_close.py
odoo_addons/account_journal_period_close/view/account_period_view.xml
